<?xml version="1.0" encoding="utf-8" ?>
<webExtender>
  <urls>
    <alias name="chrome">chrome://maplus/content</alias>
    <alias name="melior">http://meliorannis.idnes.cz</alias>
  </urls>
  <extenders>
    <script url="#{melior}/*" name="interop.js" />

    <!-- Generic -->
    <script url="#{melior}/*" name="tooltip.js" />
    <script url="#{melior}/*" name="lib.js" />
    
    <style url="#{melior}/*" src="#{chrome}/html/maplus.css" />
    <script url="#{melior}/*" name="analyza.js" />
    <script url="#{melior}/*" name="config.js" />
    <script url="#{melior}/*" name="maplus.js" />
    
    <script url="#{melior}/*" name="menu.js" />
    
    <!-- Specific -->
    <script url="#{melior}/obchod.html" name="bestiar.js" />
    <script url="#{melior}/magie.html" name="magie.js" />
    <script url="#{melior}/aliance.html" name="aliance.js" />
    <script url="#{melior}/armada.html" name="armada.js" />
    <script url="#{melior}/odmeny.html" name="blacklist.js" />
    <script url="#{melior}/setup.html" name="obrana.js" />
    <script url="#{melior}/setup.html" name="spehove.js" />
    <script url="#{melior}/banka.html" name="banka.js" />
    <script url="#{melior}/status.html" name="hospodarstvi.js" />
    <script url="#{melior}/main.html" name="utoky.js" />
    
    <script url="#{melior}/main.html" name="nastaveni.js" />

    <!-- Post processing -->
    <script url="#{melior}/*" name="postprocessing.js" />
    <script url="#{melior}/*" name="theme.js" />
  </extenders>
</webExtender>
